LICENSE
pyblock_builder/__init__.py
pyblock_builder/blocks/__init__.py
pyblock_builder/blocks/actions.py
pyblock_builder/blocks/context.py
pyblock_builder/blocks/divider.py
pyblock_builder/blocks/file.py
pyblock_builder/blocks/header.py
pyblock_builder/blocks/image.py
pyblock_builder/blocks/input.py
pyblock_builder/blocks/section.py
pyblock_builder/blocks/video.py
pyblock_builder/elements/__init__.py
pyblock_builder/elements/button.py
pyblock_builder/elements/checkboxes.py
pyblock_builder/elements/date_picker.py
pyblock_builder/elements/datetime_picker.py
pyblock_builder/elements/email_input.py
pyblock_builder/elements/image.py
pyblock_builder/elements/multiselect_menu.py
pyblock_builder/elements/number_input.py
pyblock_builder/elements/overflow_menu.py
pyblock_builder/elements/plain_text_input.py
pyblock_builder/elements/radio_buttons.py
pyblock_builder/elements/select_menu.py
pyblock_builder/elements/time_picker.py
pyblock_builder/elements/url_input.py
pyblock_builder/mrkdwn/__init__.py
pyblock_builder/mrkdwn/md.py
pyblock_builder/objects/__init__.py
pyblock_builder/objects/confirmation_dialog.py
pyblock_builder/objects/conversations_filter.py
pyblock_builder/objects/dispatch_action_configuration.py
pyblock_builder/objects/fields.py
pyblock_builder/objects/option.py
pyblock_builder/objects/option_group.py
pyblock_builder/objects/text.py
pyblock_builder/surfaces/__init__.py
pyblock_builder/surfaces/app_home.py
pyblock_builder/surfaces/message.py
pyblock_builder/surfaces/modal.py
pyblock_builder-0.2.9.dist-info/LICENSE
pyblock_builder-0.2.9.dist-info/METADATA
pyblock_builder-0.2.9.dist-info/WHEEL
pyblock_builder-0.2.9.dist-info/RECORD
