Metadata-Version: 2.1
Name: pyblock-builder
Version: 0.2.9
Summary: A lightweight Python library with a declarative syntax for simplifying building apps using Slack's Block Kit UI framework
Home-page: https://github.com/codywb/slack-pyblock-builder
License: BSD-3-Clause
Keywords: slack-pyblock-builder,pyblock-builder,slack,bolt,pyblock,blockkit
Author: codywb
Author-email: codybranscum@gmail.com
Requires-Python: >=3.10,<4.0
Classifier: License :: OSI Approved :: BSD License
Classifier: Operating System :: OS Independent
Classifier: Programming Language :: Python :: 3
Classifier: Programming Language :: Python :: 3.10
Classifier: Programming Language :: Python :: 3.11
Classifier: Programming Language :: Python :: 3.12
Classifier: Topic :: Software Development :: Documentation
Classifier: Topic :: Software Development :: Libraries :: Python Modules
Requires-Dist: typing-extensions
Project-URL: Repository, https://github.com/codywb/slack-pyblock-builder
